{
  "workflow_run": "127",
  "training_type": ".training-progress/nanecho-cached-ci",
  "completed_at": "2026-05-03T08:19:13.532004",
  "parameters": {
    "max_iters": 500,
    "batch_size": 2,
    "learning_rate": 0.0002,
    "model_layers": 4,
    "model_embedding": 256,
    "force_fresh_start": false
  },
  "cache_stats": {
    "total_checkpoints": 10,
    "total_size_mb": 2558.038022994995,
    "total_size_gb": 2.49808400683105,
    "best_quality_score": 1382400.7821704412,
    "best_val_loss": 0.0007223097112728283,
    "cache_dir": ".training-progress/nanecho-cached-ci/cache"
  },
  "best_checkpoint": {
    "id": "ckpt_20260503_081909_9000_22deff1b_9470fbb7",
    "quality_score": 1382400.7821704412,
    "val_loss": 0.0007223097112728283,
    "iteration": 9000,
    "created_at": "2026-05-03T08:19:09.255922"
  }
}